odoo/addons/product_dimension/README.rst
odoo/addons/product_dimension/__init__.py
odoo/addons/product_dimension/__manifest__.py
odoo/addons/product_dimension/i18n/ca.po
odoo/addons/product_dimension/i18n/de.po
odoo/addons/product_dimension/i18n/es.po
odoo/addons/product_dimension/i18n/fr.po
odoo/addons/product_dimension/i18n/fr_FR.po
odoo/addons/product_dimension/i18n/product_dimension.pot
odoo/addons/product_dimension/models/__init__.py
odoo/addons/product_dimension/models/product.py
odoo/addons/product_dimension/static/description/icon.png
odoo/addons/product_dimension/tests/__init__.py
odoo/addons/product_dimension/tests/test_compute_volume.py
odoo/addons/product_dimension/views/product_view.xml
odoo11_addon_product_dimension-11.0.1.0.0.99.dev7.dist-info/METADATA
odoo11_addon_product_dimension-11.0.1.0.0.99.dev7.dist-info/RECORD
odoo11_addon_product_dimension-11.0.1.0.0.99.dev7.dist-info/WHEEL
odoo11_addon_product_dimension-11.0.1.0.0.99.dev7.dist-info/top_level.txt
